[{"created_at":"Sat May 04 21:14:44 +0000 2013","id":3.3079263513034e+17,"id_str":"330792635130343424","text":"@rayinprague indeed, including the codex argenteus!","source":"<a href=\"http:\/\/www.tweetdeck.com\" rel=\"nofollow\">TweetDeck<\/a>","truncated":false,"in_reply_to_status_id":3.3078588934733e+17,"in_reply_to_status_id_str":"330785889347330048","in_reply_to_user_id":212890869,"in_reply_to_user_id_str":"212890869","in_reply_to_screen_name":"rayinprague","user":{"id":19663706,"id_str":"19663706","name":"@sweden \/ Joakim","screen_name":"sweden","location":"Sweden","url":"http:\/\/curatorsofsweden.com","description":"A new Swede every week \/ Aspiring forester, fond of movies, genuinely scared of puppets.","protected":false,"followers_count":66932,"friends_count":1227,"listed_count":1307,"created_at":"Wed Jan 28 17:33:09 +0000 2009","favourites_count":2774,"utc_offset":3600,"time_zone":"Stockholm","geo_enabled":true,"verified":false,"statuses_count":51867,"lang":"en","contributors_enabled":false,"is_translator":false,"profile_background_color":"FFFAE6","profile_background_image_url":"http:\/\/a0.twimg.com\/images\/themes\/theme1\/bg.png","profile_background_image_url_https":"https:\/\/si0.twimg.com\/images\/themes\/theme1\/bg.png","profile_background_tile":false,"profile_image_url":"http:\/\/a0.twimg.com\/profile_images\/3590043526\/db264ebc82b2c64e10eb35b0f0a42d6a_normal.png","profile_image_url_https":"https:\/\/si0.twimg.com\/profile_images\/3590043526\/db264ebc82b2c64e10eb35b0f0a42d6a_normal.png","profile_link_color":"0071A6","profile_sidebar_border_color":"C0DEED","profile_sidebar_fill_color":"DDEEF6","profile_text_color":"464646","profile_use_background_image":false,"default_profile":false,"default_profile_image":false,"following":null,"follow_request_sent":false,"notifications":null},"geo":null,"coordinates":null,"place":null,"contributors":null,"retweet_count":0,"favorite_count":0,"favorited":false,"retweeted":false,"lang":"en"},{"created_at":"Sat May 04 20:44:11 +0000 2013","id":3.3078494610706e+17,"id_str":"330784946107064320","text":"Czech republic is called Tjeckien in Swedish.","source":"<a href=\"http:\/\/www.tweetdeck.com\" rel=\"nofollow\">TweetDeck<\/a>","truncated":false,"in_reply_to_status_id":null,"in_reply_to_status_id_str":null,"in_reply_to_user_id":null,"in_reply_to_user_id_str":null,"in_reply_to_screen_name":null,"user":{"id":19663706,"id_str":"19663706","name":"@sweden \/ Joakim","screen_name":"sweden","location":"Sweden","url":"http:\/\/curatorsofsweden.com","description":"A new Swede every week \/ Aspiring forester, fond of movies, genuinely scared of puppets.","protected":false,"followers_count":66932,"friends_count":1227,"listed_count":1307,"created_at":"Wed Jan 28 17:33:09 +0000 2009","favourites_count":2774,"utc_offset":3600,"time_zone":"Stockholm","geo_enabled":true,"verified":false,"statuses_count":51867,"lang":"en","contributors_enabled":false,"is_translator":false,"profile_background_color":"FFFAE6","profile_background_image_url":"http:\/\/a0.twimg.com\/images\/themes\/theme1\/bg.png","profile_background_image_url_https":"https:\/\/si0.twimg.com\/images\/themes\/theme1\/bg.png","profile_background_tile":false,"profile_image_url":"http:\/\/a0.twimg.com\/profile_images\/3590043526\/db264ebc82b2c64e10eb35b0f0a42d6a_normal.png","profile_image_url_https":"https:\/\/si0.twimg.com\/profile_images\/3590043526\/db264ebc82b2c64e10eb35b0f0a42d6a_normal.png","profile_link_color":"0071A6","profile_sidebar_border_color":"C0DEED","profile_sidebar_fill_color":"DDEEF6","profile_text_color":"464646","profile_use_background_image":false,"default_profile":false,"default_profile_image":false,"following":null,"follow_request_sent":false,"notifications":null},"geo":null,"coordinates":null,"place":null,"contributors":null,"retweet_count":9,"favorite_count":5,"favorited":false,"retweeted":false,"lang":"en"},{"created_at":"Sat May 04 20:43:11 +0000 2013","id":3.3078469262849e+17,"id_str":"330784692628488192","text":"Sweden won against czech republic in the icehockey world Championships! The result, 2-1.","source":"<a href=\"http:\/\/www.tweetdeck.com\" rel=\"nofollow\">TweetDeck<\/a>","truncated":false,"in_reply_to_status_id":null,"in_reply_to_status_id_str":null,"in_reply_to_user_id":null,"in_reply_to_user_id_str":null,"in_reply_to_screen_name":null,"user":{"id":19663706,"id_str":"19663706","name":"@sweden \/ Joakim","screen_name":"sweden","location":"Sweden","url":"http:\/\/curatorsofsweden.com","description":"A new Swede every week \/ Aspiring forester, fond of movies, genuinely scared of puppets.","protected":false,"followers_count":66932,"friends_count":1227,"listed_count":1307,"created_at":"Wed Jan 28 17:33:09 +0000 2009","favourites_count":2774,"utc_offset":3600,"time_zone":"Stockholm","geo_enabled":true,"verified":false,"statuses_count":51867,"lang":"en","contributors_enabled":false,"is_translator":false,"profile_background_color":"FFFAE6","profile_background_image_url":"http:\/\/a0.twimg.com\/images\/themes\/theme1\/bg.png","profile_background_image_url_https":"https:\/\/si0.twimg.com\/images\/themes\/theme1\/bg.png","profile_background_tile":false,"profile_image_url":"http:\/\/a0.twimg.com\/profile_images\/3590043526\/db264ebc82b2c64e10eb35b0f0a42d6a_normal.png","profile_image_url_https":"https:\/\/si0.twimg.com\/profile_images\/3590043526\/db264ebc82b2c64e10eb35b0f0a42d6a_normal.png","profile_link_color":"0071A6","profile_sidebar_border_color":"C0DEED","profile_sidebar_fill_color":"DDEEF6","profile_text_color":"464646","profile_use_background_image":false,"default_profile":false,"default_profile_image":false,"following":null,"follow_request_sent":false,"notifications":null},"geo":null,"coordinates":null,"place":null,"contributors":null,"retweet_count":5,"favorite_count":2,"favorited":false,"retweeted":false,"lang":"en"},{"created_at":"Sat May 04 19:49:29 +0000 2013","id":3.3077117876977e+17,"id_str":"330771178769772544","text":"Sweden is in the lead 2 to 1 against czech republic!","source":"<a href=\"http:\/\/www.tweetdeck.com\" rel=\"nofollow\">TweetDeck<\/a>","truncated":false,"in_reply_to_status_id":null,"in_reply_to_status_id_str":null,"in_reply_to_user_id":null,"in_reply_to_user_id_str":null,"in_reply_to_screen_name":null,"user":{"id":19663706,"id_str":"19663706","name":"@sweden \/ Joakim","screen_name":"sweden","location":"Sweden","url":"http:\/\/curatorsofsweden.com","description":"A new Swede every week \/ Aspiring forester, fond of movies, genuinely scared of puppets.","protected":false,"followers_count":66932,"friends_count":1227,"listed_count":1307,"created_at":"Wed Jan 28 17:33:09 +0000 2009","favourites_count":2774,"utc_offset":3600,"time_zone":"Stockholm","geo_enabled":true,"verified":false,"statuses_count":51867,"lang":"en","contributors_enabled":false,"is_translator":false,"profile_background_color":"FFFAE6","profile_background_image_url":"http:\/\/a0.twimg.com\/images\/themes\/theme1\/bg.png","profile_background_image_url_https":"https:\/\/si0.twimg.com\/images\/themes\/theme1\/bg.png","profile_background_tile":false,"profile_image_url":"http:\/\/a0.twimg.com\/profile_images\/3590043526\/db264ebc82b2c64e10eb35b0f0a42d6a_normal.png","profile_image_url_https":"https:\/\/si0.twimg.com\/profile_images\/3590043526\/db264ebc82b2c64e10eb35b0f0a42d6a_normal.png","profile_link_color":"0071A6","profile_sidebar_border_color":"C0DEED","profile_sidebar_fill_color":"DDEEF6","profile_text_color":"464646","profile_use_background_image":false,"default_profile":false,"default_profile_image":false,"following":null,"follow_request_sent":false,"notifications":null},"geo":null,"coordinates":null,"place":null,"contributors":null,"retweet_count":6,"favorite_count":5,"favorited":false,"retweeted":false,"lang":"en"},{"created_at":"Sat May 04 15:41:32 +0000 2013","id":3.3070878098575e+17,"id_str":"330708780985753600","text":"@Archiedalo Not really, sorry. Try the iihf webpage. Maybe it say something.","source":"<a href=\"http:\/\/www.tweetdeck.com\" rel=\"nofollow\">TweetDeck<\/a>","truncated":false,"in_reply_to_status_id":3.3069925118314e+17,"in_reply_to_status_id_str":"330699251183136771","in_reply_to_user_id":578863925,"in_reply_to_user_id_str":"578863925","in_reply_to_screen_name":"Archiedalo","user":{"id":19663706,"id_str":"19663706","name":"@sweden \/ Joakim","screen_name":"sweden","location":"Sweden","url":"http:\/\/curatorsofsweden.com","description":"A new Swede every week \/ Aspiring forester, fond of movies, genuinely scared of puppets.","protected":false,"followers_count":66932,"friends_count":1227,"listed_count":1307,"created_at":"Wed Jan 28 17:33:09 +0000 2009","favourites_count":2774,"utc_offset":3600,"time_zone":"Stockholm","geo_enabled":true,"verified":false,"statuses_count":51867,"lang":"en","contributors_enabled":false,"is_translator":false,"profile_background_color":"FFFAE6","profile_background_image_url":"http:\/\/a0.twimg.com\/images\/themes\/theme1\/bg.png","profile_background_image_url_https":"https:\/\/si0.twimg.com\/images\/themes\/theme1\/bg.png","profile_background_tile":false,"profile_image_url":"http:\/\/a0.twimg.com\/profile_images\/3590043526\/db264ebc82b2c64e10eb35b0f0a42d6a_normal.png","profile_image_url_https":"https:\/\/si0.twimg.com\/profile_images\/3590043526\/db264ebc82b2c64e10eb35b0f0a42d6a_normal.png","profile_link_color":"0071A6","profile_sidebar_border_color":"C0DEED","profile_sidebar_fill_color":"DDEEF6","profile_text_color":"464646","profile_use_background_image":false,"default_profile":false,"default_profile_image":false,"following":null,"follow_request_sent":false,"notifications":null},"geo":null,"coordinates":null,"place":null,"contributors":null,"retweet_count":0,"favorite_count":0,"favorited":false,"retweeted":false,"lang":"en"},{"created_at":"Sat May 04 14:49:51 +0000 2013","id":3.306957767098e+17,"id_str":"330695776709795840","text":"@itsgravy_baby Me too! But my poster is neatly folded inside the cover","source":"<a href=\"http:\/\/www.tweetdeck.com\" rel=\"nofollow\">TweetDeck<\/a>","truncated":false,"in_reply_to_status_id":3.3069447066223e+17,"in_reply_to_status_id_str":"330694470662225921","in_reply_to_user_id":35081844,"in_reply_to_user_id_str":"35081844","in_reply_to_screen_name":"itsgravy_baby","user":{"id":19663706,"id_str":"19663706","name":"@sweden \/ Joakim","screen_name":"sweden","location":"Sweden","url":"http:\/\/curatorsofsweden.com","description":"A new Swede every week \/ Aspiring forester, fond of movies, genuinely scared of puppets.","protected":false,"followers_count":66932,"friends_count":1227,"listed_count":1307,"created_at":"Wed Jan 28 17:33:09 +0000 2009","favourites_count":2774,"utc_offset":3600,"time_zone":"Stockholm","geo_enabled":true,"verified":false,"statuses_count":51867,"lang":"en","contributors_enabled":false,"is_translator":false,"profile_background_color":"FFFAE6","profile_background_image_url":"http:\/\/a0.twimg.com\/images\/themes\/theme1\/bg.png","profile_background_image_url_https":"https:\/\/si0.twimg.com\/images\/themes\/theme1\/bg.png","profile_background_tile":false,"profile_image_url":"http:\/\/a0.twimg.com\/profile_images\/3590043526\/db264ebc82b2c64e10eb35b0f0a42d6a_normal.png","profile_image_url_https":"https:\/\/si0.twimg.com\/profile_images\/3590043526\/db264ebc82b2c64e10eb35b0f0a42d6a_normal.png","profile_link_color":"0071A6","profile_sidebar_border_color":"C0DEED","profile_sidebar_fill_color":"DDEEF6","profile_text_color":"464646","profile_use_background_image":false,"default_profile":false,"default_profile_image":false,"following":null,"follow_request_sent":false,"notifications":null},"geo":null,"coordinates":null,"place":null,"contributors":null,"retweet_count":0,"favorite_count":0,"favorited":false,"retweeted":false,"lang":"en"},{"created_at":"Sat May 04 14:46:42 +0000 2013","id":3.3069498074834e+17,"id_str":"330694980748337152","text":"@Wharfrat1983 Blessed are the cheesemakers.","source":"<a href=\"http:\/\/www.tweetdeck.com\" rel=\"nofollow\">TweetDeck<\/a>","truncated":false,"in_reply_to_status_id":3.3069433176368e+17,"in_reply_to_status_id_str":"330694331763683328","in_reply_to_user_id":194015879,"in_reply_to_user_id_str":"194015879","in_reply_to_screen_name":"Wharfrat1983","user":{"id":19663706,"id_str":"19663706","name":"@sweden \/ Joakim","screen_name":"sweden","location":"Sweden","url":"http:\/\/curatorsofsweden.com","description":"A new Swede every week \/ Aspiring forester, fond of movies, genuinely scared of puppets.","protected":false,"followers_count":66932,"friends_count":1227,"listed_count":1307,"created_at":"Wed Jan 28 17:33:09 +0000 2009","favourites_count":2774,"utc_offset":3600,"time_zone":"Stockholm","geo_enabled":true,"verified":false,"statuses_count":51867,"lang":"en","contributors_enabled":false,"is_translator":false,"profile_background_color":"FFFAE6","profile_background_image_url":"http:\/\/a0.twimg.com\/images\/themes\/theme1\/bg.png","profile_background_image_url_https":"https:\/\/si0.twimg.com\/images\/themes\/theme1\/bg.png","profile_background_tile":false,"profile_image_url":"http:\/\/a0.twimg.com\/profile_images\/3590043526\/db264ebc82b2c64e10eb35b0f0a42d6a_normal.png","profile_image_url_https":"https:\/\/si0.twimg.com\/profile_images\/3590043526\/db264ebc82b2c64e10eb35b0f0a42d6a_normal.png","profile_link_color":"0071A6","profile_sidebar_border_color":"C0DEED","profile_sidebar_fill_color":"DDEEF6","profile_text_color":"464646","profile_use_background_image":false,"default_profile":false,"default_profile_image":false,"following":null,"follow_request_sent":false,"notifications":null},"geo":null,"coordinates":null,"place":null,"contributors":null,"retweet_count":0,"favorite_count":0,"favorited":false,"retweeted":false,"lang":"en"},{"created_at":"Sat May 04 14:45:56 +0000 2013","id":3.306947913042e+17,"id_str":"330694791304200193","text":"@Swipsey men dit hoppas vi att det dr\u00f6jer l\u00e4nge :)","source":"<a href=\"http:\/\/www.tweetdeck.com\" rel=\"nofollow\">TweetDeck<\/a>","truncated":false,"in_reply_to_status_id":3.3069385669165e+17,"in_reply_to_status_id_str":"330693856691646465","in_reply_to_user_id":480767921,"in_reply_to_user_id_str":"480767921","in_reply_to_screen_name":"Swipsey","user":{"id":19663706,"id_str":"19663706","name":"@sweden \/ Joakim","screen_name":"sweden","location":"Sweden","url":"http:\/\/curatorsofsweden.com","description":"A new Swede every week \/ Aspiring forester, fond of movies, genuinely scared of puppets.","protected":false,"followers_count":66932,"friends_count":1227,"listed_count":1307,"created_at":"Wed Jan 28 17:33:09 +0000 2009","favourites_count":2774,"utc_offset":3600,"time_zone":"Stockholm","geo_enabled":true,"verified":false,"statuses_count":51867,"lang":"en","contributors_enabled":false,"is_translator":false,"profile_background_color":"FFFAE6","profile_background_image_url":"http:\/\/a0.twimg.com\/images\/themes\/theme1\/bg.png","profile_background_image_url_https":"https:\/\/si0.twimg.com\/images\/themes\/theme1\/bg.png","profile_background_tile":false,"profile_image_url":"http:\/\/a0.twimg.com\/profile_images\/3590043526\/db264ebc82b2c64e10eb35b0f0a42d6a_normal.png","profile_image_url_https":"https:\/\/si0.twimg.com\/profile_images\/3590043526\/db264ebc82b2c64e10eb35b0f0a42d6a_normal.png","profile_link_color":"0071A6","profile_sidebar_border_color":"C0DEED","profile_sidebar_fill_color":"DDEEF6","profile_text_color":"464646","profile_use_background_image":false,"default_profile":false,"default_profile_image":false,"following":null,"follow_request_sent":false,"notifications":null},"geo":null,"coordinates":null,"place":null,"contributors":null,"retweet_count":0,"favorite_count":0,"favorited":false,"retweeted":false,"lang":"sv"},{"created_at":"Sat May 04 14:22:06 +0000 2013","id":3.3068879179273e+17,"id_str":"330688791792730112","text":"@scaryduck Haha! What a nice story to tell the grand children! I would very much like to have see him perform. Sad thing that he passed away","source":"<a href=\"http:\/\/www.tweetdeck.com\" rel=\"nofollow\">TweetDeck<\/a>","truncated":false,"in_reply_to_status_id":3.3068686802068e+17,"in_reply_to_status_id_str":"330686868020682753","in_reply_to_user_id":57233,"in_reply_to_user_id_str":"57233","in_reply_to_screen_name":"scaryduck","user":{"id":19663706,"id_str":"19663706","name":"@sweden \/ Joakim","screen_name":"sweden","location":"Sweden","url":"http:\/\/curatorsofsweden.com","description":"A new Swede every week \/ Aspiring forester, fond of movies, genuinely scared of puppets.","protected":false,"followers_count":66932,"friends_count":1227,"listed_count":1307,"created_at":"Wed Jan 28 17:33:09 +0000 2009","favourites_count":2774,"utc_offset":3600,"time_zone":"Stockholm","geo_enabled":true,"verified":false,"statuses_count":51867,"lang":"en","contributors_enabled":false,"is_translator":false,"profile_background_color":"FFFAE6","profile_background_image_url":"http:\/\/a0.twimg.com\/images\/themes\/theme1\/bg.png","profile_background_image_url_https":"https:\/\/si0.twimg.com\/images\/themes\/theme1\/bg.png","profile_background_tile":false,"profile_image_url":"http:\/\/a0.twimg.com\/profile_images\/3590043526\/db264ebc82b2c64e10eb35b0f0a42d6a_normal.png","profile_image_url_https":"https:\/\/si0.twimg.com\/profile_images\/3590043526\/db264ebc82b2c64e10eb35b0f0a42d6a_normal.png","profile_link_color":"0071A6","profile_sidebar_border_color":"C0DEED","profile_sidebar_fill_color":"DDEEF6","profile_text_color":"464646","profile_use_background_image":false,"default_profile":false,"default_profile_image":false,"following":null,"follow_request_sent":false,"notifications":null},"geo":null,"coordinates":null,"place":null,"contributors":null,"retweet_count":0,"favorite_count":0,"favorited":false,"retweeted":false,"lang":"en"},{"created_at":"Sat May 04 14:17:56 +0000 2013","id":3.3068774433243e+17,"id_str":"330687744332427264","text":"George Harrison also had a major role in the making of monty pythons life of Brian. The funniest film I've ever watched. Great comedy.","source":"<a href=\"http:\/\/www.tweetdeck.com\" rel=\"nofollow\">TweetDeck<\/a>","truncated":false,"in_reply_to_status_id":null,"in_reply_to_status_id_str":null,"in_reply_to_user_id":null,"in_reply_to_user_id_str":null,"in_reply_to_screen_name":null,"user":{"id":19663706,"id_str":"19663706","name":"@sweden \/ Joakim","screen_name":"sweden","location":"Sweden","url":"http:\/\/curatorsofsweden.com","description":"A new Swede every week \/ Aspiring forester, fond of movies, genuinely scared of puppets.","protected":false,"followers_count":66932,"friends_count":1227,"listed_count":1307,"created_at":"Wed Jan 28 17:33:09 +0000 2009","favourites_count":2774,"utc_offset":3600,"time_zone":"Stockholm","geo_enabled":true,"verified":false,"statuses_count":51867,"lang":"en","contributors_enabled":false,"is_translator":false,"profile_background_color":"FFFAE6","profile_background_image_url":"http:\/\/a0.twimg.com\/images\/themes\/theme1\/bg.png","profile_background_image_url_https":"https:\/\/si0.twimg.com\/images\/themes\/theme1\/bg.png","profile_background_tile":false,"profile_image_url":"http:\/\/a0.twimg.com\/profile_images\/3590043526\/db264ebc82b2c64e10eb35b0f0a42d6a_normal.png","profile_image_url_https":"https:\/\/si0.twimg.com\/profile_images\/3590043526\/db264ebc82b2c64e10eb35b0f0a42d6a_normal.png","profile_link_color":"0071A6","profile_sidebar_border_color":"C0DEED","profile_sidebar_fill_color":"DDEEF6","profile_text_color":"464646","profile_use_background_image":false,"default_profile":false,"default_profile_image":false,"following":null,"follow_request_sent":false,"notifications":null},"geo":null,"coordinates":null,"place":null,"contributors":null,"retweet_count":5,"favorite_count":5,"favorited":false,"retweeted":false,"lang":"en"},{"created_at":"Sat May 04 14:13:41 +0000 2013","id":3.3068667168529e+17,"id_str":"330686671685292032","text":"@kobkob333 I guess that the scientists who named them thought they were most common in those countries.","source":"<a href=\"http:\/\/www.tweetdeck.com\" rel=\"nofollow\">TweetDeck<\/a>","truncated":false,"in_reply_to_status_id":3.3068553701283e+17,"in_reply_to_status_id_str":"330685537012834304","in_reply_to_user_id":366299448,"in_reply_to_user_id_str":"366299448","in_reply_to_screen_name":"kobkob333","user":{"id":19663706,"id_str":"19663706","name":"@sweden \/ Joakim","screen_name":"sweden","location":"Sweden","url":"http:\/\/curatorsofsweden.com","description":"A new Swede every week \/ Aspiring forester, fond of movies, genuinely scared of puppets.","protected":false,"followers_count":66932,"friends_count":1227,"listed_count":1307,"created_at":"Wed Jan 28 17:33:09 +0000 2009","favourites_count":2774,"utc_offset":3600,"time_zone":"Stockholm","geo_enabled":true,"verified":false,"statuses_count":51867,"lang":"en","contributors_enabled":false,"is_translator":false,"profile_background_color":"FFFAE6","profile_background_image_url":"http:\/\/a0.twimg.com\/images\/themes\/theme1\/bg.png","profile_background_image_url_https":"https:\/\/si0.twimg.com\/images\/themes\/theme1\/bg.png","profile_background_tile":false,"profile_image_url":"http:\/\/a0.twimg.com\/profile_images\/3590043526\/db264ebc82b2c64e10eb35b0f0a42d6a_normal.png","profile_image_url_https":"https:\/\/si0.twimg.com\/profile_images\/3590043526\/db264ebc82b2c64e10eb35b0f0a42d6a_normal.png","profile_link_color":"0071A6","profile_sidebar_border_color":"C0DEED","profile_sidebar_fill_color":"DDEEF6","profile_text_color":"464646","profile_use_background_image":false,"default_profile":false,"default_profile_image":false,"following":null,"follow_request_sent":false,"notifications":null},"geo":null,"coordinates":null,"place":null,"contributors":null,"retweet_count":0,"favorite_count":0,"favorited":false,"retweeted":false,"lang":"en"},{"created_at":"Sat May 04 14:11:38 +0000 2013","id":3.3068615628923e+17,"id_str":"330686156289228800","text":"His debut solo album, all things must pass, is one of the best ones ever made in my opinion.","source":"<a href=\"http:\/\/www.tweetdeck.com\" rel=\"nofollow\">TweetDeck<\/a>","truncated":false,"in_reply_to_status_id":null,"in_reply_to_status_id_str":null,"in_reply_to_user_id":null,"in_reply_to_user_id_str":null,"in_reply_to_screen_name":null,"user":{"id":19663706,"id_str":"19663706","name":"@sweden \/ Joakim","screen_name":"sweden","location":"Sweden","url":"http:\/\/curatorsofsweden.com","description":"A new Swede every week \/ Aspiring forester, fond of movies, genuinely scared of puppets.","protected":false,"followers_count":66932,"friends_count":1227,"listed_count":1307,"created_at":"Wed Jan 28 17:33:09 +0000 2009","favourites_count":2774,"utc_offset":3600,"time_zone":"Stockholm","geo_enabled":true,"verified":false,"statuses_count":51867,"lang":"en","contributors_enabled":false,"is_translator":false,"profile_background_color":"FFFAE6","profile_background_image_url":"http:\/\/a0.twimg.com\/images\/themes\/theme1\/bg.png","profile_background_image_url_https":"https:\/\/si0.twimg.com\/images\/themes\/theme1\/bg.png","profile_background_tile":false,"profile_image_url":"http:\/\/a0.twimg.com\/profile_images\/3590043526\/db264ebc82b2c64e10eb35b0f0a42d6a_normal.png","profile_image_url_https":"https:\/\/si0.twimg.com\/profile_images\/3590043526\/db264ebc82b2c64e10eb35b0f0a42d6a_normal.png","profile_link_color":"0071A6","profile_sidebar_border_color":"C0DEED","profile_sidebar_fill_color":"DDEEF6","profile_text_color":"464646","profile_use_background_image":false,"default_profile":false,"default_profile_image":false,"following":null,"follow_request_sent":false,"notifications":null},"geo":null,"coordinates":null,"place":null,"contributors":null,"retweet_count":2,"favorite_count":5,"favorited":false,"retweeted":false,"lang":"en"},{"created_at":"Sat May 04 14:09:31 +0000 2013","id":3.306856262005e+17,"id_str":"330685626200498177","text":"Todays featured article on Wikipedia is George Harrison. My favourite musician and guitarist of all time.","source":"<a href=\"http:\/\/www.tweetdeck.com\" rel=\"nofollow\">TweetDeck<\/a>","truncated":false,"in_reply_to_status_id":null,"in_reply_to_status_id_str":null,"in_reply_to_user_id":null,"in_reply_to_user_id_str":null,"in_reply_to_screen_name":null,"user":{"id":19663706,"id_str":"19663706","name":"@sweden \/ Joakim","screen_name":"sweden","location":"Sweden","url":"http:\/\/curatorsofsweden.com","description":"A new Swede every week \/ Aspiring forester, fond of movies, genuinely scared of puppets.","protected":false,"followers_count":66932,"friends_count":1227,"listed_count":1307,"created_at":"Wed Jan 28 17:33:09 +0000 2009","favourites_count":2774,"utc_offset":3600,"time_zone":"Stockholm","geo_enabled":true,"verified":false,"statuses_count":51867,"lang":"en","contributors_enabled":false,"is_translator":false,"profile_background_color":"FFFAE6","profile_background_image_url":"http:\/\/a0.twimg.com\/images\/themes\/theme1\/bg.png","profile_background_image_url_https":"https:\/\/si0.twimg.com\/images\/themes\/theme1\/bg.png","profile_background_tile":false,"profile_image_url":"http:\/\/a0.twimg.com\/profile_images\/3590043526\/db264ebc82b2c64e10eb35b0f0a42d6a_normal.png","profile_image_url_https":"https:\/\/si0.twimg.com\/profile_images\/3590043526\/db264ebc82b2c64e10eb35b0f0a42d6a_normal.png","profile_link_color":"0071A6","profile_sidebar_border_color":"C0DEED","profile_sidebar_fill_color":"DDEEF6","profile_text_color":"464646","profile_use_background_image":false,"default_profile":false,"default_profile_image":false,"following":null,"follow_request_sent":false,"notifications":null},"geo":null,"coordinates":null,"place":null,"contributors":null,"retweet_count":5,"favorite_count":3,"favorited":false,"retweeted":false,"lang":"en"},{"created_at":"Sat May 04 13:19:44 +0000 2013","id":3.3067309721046e+17,"id_str":"330673097210462209","text":"There is an additional 6 million hectares that is not used for production.","source":"<a href=\"http:\/\/www.tweetdeck.com\" rel=\"nofollow\">TweetDeck<\/a>","truncated":false,"in_reply_to_status_id":null,"in_reply_to_status_id_str":null,"in_reply_to_user_id":null,"in_reply_to_user_id_str":null,"in_reply_to_screen_name":null,"user":{"id":19663706,"id_str":"19663706","name":"@sweden \/ Joakim","screen_name":"sweden","location":"Sweden","url":"http:\/\/curatorsofsweden.com","description":"A new Swede every week \/ Aspiring forester, fond of movies, genuinely scared of puppets.","protected":false,"followers_count":66932,"friends_count":1227,"listed_count":1307,"created_at":"Wed Jan 28 17:33:09 +0000 2009","favourites_count":2774,"utc_offset":3600,"time_zone":"Stockholm","geo_enabled":true,"verified":false,"statuses_count":51867,"lang":"en","contributors_enabled":false,"is_translator":false,"profile_background_color":"FFFAE6","profile_background_image_url":"http:\/\/a0.twimg.com\/images\/themes\/theme1\/bg.png","profile_background_image_url_https":"https:\/\/si0.twimg.com\/images\/themes\/theme1\/bg.png","profile_background_tile":false,"profile_image_url":"http:\/\/a0.twimg.com\/profile_images\/3590043526\/db264ebc82b2c64e10eb35b0f0a42d6a_normal.png","profile_image_url_https":"https:\/\/si0.twimg.com\/profile_images\/3590043526\/db264ebc82b2c64e10eb35b0f0a42d6a_normal.png","profile_link_color":"0071A6","profile_sidebar_border_color":"C0DEED","profile_sidebar_fill_color":"DDEEF6","profile_text_color":"464646","profile_use_background_image":false,"default_profile":false,"default_profile_image":false,"following":null,"follow_request_sent":false,"notifications":null},"geo":null,"coordinates":null,"place":null,"contributors":null,"retweet_count":0,"favorite_count":1,"favorited":false,"retweeted":false,"lang":"en"},{"created_at":"Sat May 04 13:17:43 +0000 2013","id":3.3067258827783e+17,"id_str":"330672588277833728","text":"Production forests, that is.","source":"<a href=\"http:\/\/www.tweetdeck.com\" rel=\"nofollow\">TweetDeck<\/a>","truncated":false,"in_reply_to_status_id":null,"in_reply_to_status_id_str":null,"in_reply_to_user_id":null,"in_reply_to_user_id_str":null,"in_reply_to_screen_name":null,"user":{"id":19663706,"id_str":"19663706","name":"@sweden \/ Joakim","screen_name":"sweden","location":"Sweden","url":"http:\/\/curatorsofsweden.com","description":"A new Swede every week \/ Aspiring forester, fond of movies, genuinely scared of puppets.","protected":false,"followers_count":66932,"friends_count":1227,"listed_count":1307,"created_at":"Wed Jan 28 17:33:09 +0000 2009","favourites_count":2774,"utc_offset":3600,"time_zone":"Stockholm","geo_enabled":true,"verified":false,"statuses_count":51867,"lang":"en","contributors_enabled":false,"is_translator":false,"profile_background_color":"FFFAE6","profile_background_image_url":"http:\/\/a0.twimg.com\/images\/themes\/theme1\/bg.png","profile_background_image_url_https":"https:\/\/si0.twimg.com\/images\/themes\/theme1\/bg.png","profile_background_tile":false,"profile_image_url":"http:\/\/a0.twimg.com\/profile_images\/3590043526\/db264ebc82b2c64e10eb35b0f0a42d6a_normal.png","profile_image_url_https":"https:\/\/si0.twimg.com\/profile_images\/3590043526\/db264ebc82b2c64e10eb35b0f0a42d6a_normal.png","profile_link_color":"0071A6","profile_sidebar_border_color":"C0DEED","profile_sidebar_fill_color":"DDEEF6","profile_text_color":"464646","profile_use_background_image":false,"default_profile":false,"default_profile_image":false,"following":null,"follow_request_sent":false,"notifications":null},"geo":null,"coordinates":null,"place":null,"contributors":null,"retweet_count":0,"favorite_count":0,"favorited":false,"retweeted":false,"lang":"en"},{"created_at":"Sat May 04 13:15:11 +0000 2013","id":3.3067195196836e+17,"id_str":"330671951968362496","text":"Swedens forests take up 22,7 milion hectares.","source":"<a href=\"http:\/\/www.tweetdeck.com\" rel=\"nofollow\">TweetDeck<\/a>","truncated":false,"in_reply_to_status_id":null,"in_reply_to_status_id_str":null,"in_reply_to_user_id":null,"in_reply_to_user_id_str":null,"in_reply_to_screen_name":null,"user":{"id":19663706,"id_str":"19663706","name":"@sweden \/ Joakim","screen_name":"sweden","location":"Sweden","url":"http:\/\/curatorsofsweden.com","description":"A new Swede every week \/ Aspiring forester, fond of movies, genuinely scared of puppets.","protected":false,"followers_count":66932,"friends_count":1227,"listed_count":1307,"created_at":"Wed Jan 28 17:33:09 +0000 2009","favourites_count":2774,"utc_offset":3600,"time_zone":"Stockholm","geo_enabled":true,"verified":false,"statuses_count":51867,"lang":"en","contributors_enabled":false,"is_translator":false,"profile_background_color":"FFFAE6","profile_background_image_url":"http:\/\/a0.twimg.com\/images\/themes\/theme1\/bg.png","profile_background_image_url_https":"https:\/\/si0.twimg.com\/images\/themes\/theme1\/bg.png","profile_background_tile":false,"profile_image_url":"http:\/\/a0.twimg.com\/profile_images\/3590043526\/db264ebc82b2c64e10eb35b0f0a42d6a_normal.png","profile_image_url_https":"https:\/\/si0.twimg.com\/profile_images\/3590043526\/db264ebc82b2c64e10eb35b0f0a42d6a_normal.png","profile_link_color":"0071A6","profile_sidebar_border_color":"C0DEED","profile_sidebar_fill_color":"DDEEF6","profile_text_color":"464646","profile_use_background_image":false,"default_profile":false,"default_profile_image":false,"following":null,"follow_request_sent":false,"notifications":null},"geo":null,"coordinates":null,"place":null,"contributors":null,"retweet_count":5,"favorite_count":1,"favorited":false,"retweeted":false,"lang":"en"}]